{
    "name":  "skills-backend-api-design",
    "main_hub":  "backend",
    "sub_hub":  "api-design",
    "description":  "API design: REST, GraphQL, and best practices for scalable web services",
    "skill_count":  47,
    "src_count":  2,
    "top_triggers":  [
                         "api",
                         "documentation",
                         "patterns",
                         "dev",
                         "azure",
                         "development",
                         "builder",
                         "architecture",
                         "graphql",
                         "dotnet",
                         "ai",
                         "mgmt",
                         "expert",
                         "odoo",
                         "fp",
                         "architect",
                         "gemini",
                         "database",
                         "backend",
                         "bdistill"
                     ],
    "generated_at":  "2026-03-27T12:54:05+02:00",
    "files":  {
                  "skill":  "SKILL.md",
                  "workflow":  "workflow.md",
                  "index":  "skills-index.json",
                  "catalog":  "skills-catalog.ndjson"
              }
}
