{
    "name":  "skills-marketing-email",
    "main_hub":  "marketing",
    "sub_hub":  "email",
    "description":  "Email marketing: campaigns, automation, segmentation, and subscriber engagement strategies",
    "skill_count":  9,
    "src_count":  3,
    "top_triggers":  [
                         "email",
                         "systems",
                         "internal",
                         "curation",
                         "prevention",
                         "automation",
                         "creation",
                         "bible",
                         "cold",
                         "newsletter",
                         "churn",
                         "comms",
                         "sequence",
                         "marketing",
                         "mailchimp",
                         "revops"
                     ],
    "generated_at":  "2026-03-27T14:01:18+02:00",
    "files":  {
                  "skill":  "SKILL.md",
                  "workflow":  "workflow.md",
                  "index":  "skills-index.json",
                  "catalog":  "skills-catalog.ndjson"
              }
}
