{
    "name":  "skills-frontend-web-basics",
    "main_hub":  "frontend",
    "sub_hub":  "web-basics",
    "description":  "Web fundamentals: HTML, CSS, JavaScript, accessibility, and web standards",
    "skill_count":  18,
    "src_count":  4,
    "top_triggers":  [
                         "gsap",
                         "netlify",
                         "fixing",
                         "edge",
                         "slides",
                         "algorithmic",
                         "frontend",
                         "development",
                         "core",
                         "health",
                         "official",
                         "performance",
                         "vitepress",
                         "pdf",
                         "analyzer",
                         "factory",
                         "xss",
                         "patterns",
                         "react",
                         "tailwind"
                     ],
    "generated_at":  "2026-03-27T10:44:27+02:00",
    "files":  {
                  "skill":  "SKILL.md",
                  "workflow":  "workflow.md",
                  "index":  "skills-index.json",
                  "catalog":  "skills-catalog.ndjson"
              }
}
